cobalt_sdk/__init__.py
cobalt_sdk/client.py
cobalt_sdk/illumiere.py
cobalt_sdk/lib.py
cobalt_sdk/types.py
cobalt_sdk-0.4.2.dist-info/METADATA
cobalt_sdk-0.4.2.dist-info/WHEEL
cobalt_sdk-0.4.2.dist-info/RECORD
