Metadata-Version: 2.4
Name: cobalt-sdk
Version: 0.4.2
Summary: Python API for the Cobalt perception stack
Project-URL: Homepage, https://github.com/ceptontech/cobalt
Project-URL: Repository, https://github.com/ceptontech/cobalt.git
Project-URL: Issues, https://github.com/ceptontech/cobalt/issues
Author-email: Will Lauer <will.lauer@cepton.com>
Classifier: Development Status :: 3 - Alpha
Classifier: Intended Audience :: Developers
Classifier: License :: OSI Approved :: MIT License
Classifier: Programming Language :: Python :: 3
Classifier: Programming Language :: Python :: 3.8
Classifier: Programming Language :: Python :: 3.9
Classifier: Programming Language :: Python :: 3.10
Classifier: Programming Language :: Python :: 3.11
Classifier: Programming Language :: Python :: 3.12
Requires-Python: >=3.8
Requires-Dist: numpy
Requires-Dist: websockets
Provides-Extra: dev
Requires-Dist: black>=22.0; extra == 'dev'
Requires-Dist: flake8>=4.0; extra == 'dev'
Requires-Dist: mypy>=0.950; extra == 'dev'
Requires-Dist: pytest>=7.0; extra == 'dev'
